otp_signal/__init__.py
otp_signal/admin.py
otp_signal/conf.py
otp_signal/models.py
otp_signal/tests.py
otp_signal/migrations/0001_initial.py
otp_signal/migrations/__init__.py
django_otp_signal-0.1.0.dist-info/LICENSE
django_otp_signal-0.1.0.dist-info/METADATA
django_otp_signal-0.1.0.dist-info/WHEEL
django_otp_signal-0.1.0.dist-info/top_level.txt
django_otp_signal-0.1.0.dist-info/RECORD
