Metadata-Version: 2.1
Name: django-otp-signal
Version: 0.1.0
Summary: A django-otp plugin that delivers tokens via Signal
Home-page: https://github.com/arjan-s/django-otp-signal
Author: arjan5
Author-email: github@anymore.nl
License: BSD
Project-URL: Documentation, https://django-otp-signal.readthedocs.io/
Project-URL: Source, https://github.com/arjan-s/django-otp-signal
Classifier: Development Status :: 5 - Production/Stable
Classifier: Programming Language :: Python :: 3
Classifier: Programming Language :: Python :: 3 :: Only
Classifier: Intended Audience :: Developers
Classifier: License :: OSI Approved :: BSD License
Classifier: Topic :: Security
Classifier: Topic :: Software Development :: Libraries :: Python Modules
Classifier: Framework :: Django
License-File: LICENSE
Requires-Dist: django-otp >=0.9.2
Requires-Dist: pysignalclirestapi >=0.3.21
